distribute_setup.py
setup.py
viren/__init__.py
viren/tests.py
viren/viren.py
viren.egg-info/PKG-INFO
viren.egg-info/SOURCES.txt
viren.egg-info/dependency_links.txt
viren.egg-info/entry_points.txt
viren.egg-info/top_level.txt