Metadata-Version: 1.1
Name: viren
Version: 0.1.1-20131212
Summary: bulk-rename files using your editor
Home-page: https://github.com/cberzan/viren
Author: Constantin Berzan
Author-email: cberzan@gmail.com
License: MIT
Keywords: rename
Platform: UNKNOWN
Classifier: Development Status :: 3 - Alpha
Classifier: Intended Audience :: Developers
Classifier: License :: OSI Approved :: MIT License
Classifier: Operating System :: POSIX
Classifier: Programming Language :: Python :: 2.7
